aucmedi/__init__.py
aucmedi/automl/__init__.py
aucmedi/automl/block_eval.py
aucmedi/automl/block_pred.py
aucmedi/automl/block_train.py
aucmedi/automl/cli.py
aucmedi/automl/main.py
aucmedi/automl/parser_cli.py
aucmedi/automl/parser_yaml.py
aucmedi/data_processing/__init__.py
aucmedi/data_processing/data_generator.py
aucmedi/data_processing/io_data.py
aucmedi/data_processing/augmentation/__init__.py
aucmedi/data_processing/augmentation/aug_batchgenerators.py
aucmedi/data_processing/augmentation/aug_image.py
aucmedi/data_processing/augmentation/aug_volume.py
aucmedi/data_processing/io_interfaces/__init__.py
aucmedi/data_processing/io_interfaces/io_csv.py
aucmedi/data_processing/io_interfaces/io_directory.py
aucmedi/data_processing/io_interfaces/io_json.py
aucmedi/data_processing/io_loader/__init__.py
aucmedi/data_processing/io_loader/cache_loader.py
aucmedi/data_processing/io_loader/image_loader.py
aucmedi/data_processing/io_loader/numpy_loader.py
aucmedi/data_processing/io_loader/sitk_loader.py
aucmedi/data_processing/subfunctions/__init__.py
aucmedi/data_processing/subfunctions/chromer.py
aucmedi/data_processing/subfunctions/clip.py
aucmedi/data_processing/subfunctions/color_constancy.py
aucmedi/data_processing/subfunctions/crop.py
aucmedi/data_processing/subfunctions/padding.py
aucmedi/data_processing/subfunctions/resize.py
aucmedi/data_processing/subfunctions/sf_base.py
aucmedi/data_processing/subfunctions/standardize.py
aucmedi/ensemble/__init__.py
aucmedi/ensemble/augmenting.py
aucmedi/ensemble/bagging.py
aucmedi/ensemble/composite.py
aucmedi/ensemble/stacking.py
aucmedi/ensemble/aggregate/__init__.py
aucmedi/ensemble/aggregate/agg_base.py
aucmedi/ensemble/aggregate/averaging_mean.py
aucmedi/ensemble/aggregate/averaging_median.py
aucmedi/ensemble/aggregate/global_argmax.py
aucmedi/ensemble/aggregate/majority_vote.py
aucmedi/ensemble/aggregate/softmax.py
aucmedi/ensemble/metalearner/__init__.py
aucmedi/ensemble/metalearner/averaging_mean_weighted.py
aucmedi-0.10.0.dist-info/LICENSE.md
aucmedi-0.10.0.dist-info/METADATA
aucmedi-0.10.0.dist-info/WHEEL
aucmedi-0.10.0.dist-info/entry_points.txt
aucmedi-0.10.0.dist-info/top_level.txt
aucmedi-0.10.0.dist-info/RECORD
