Metadata-Version: 2.1
Name: aucmedi
Version: 0.10.0
Summary: AUCMEDI - a framework for Automated Classification of Medical Images
Home-page: https://frankkramer-lab.github.io/aucmedi/
Author: Dominik Müller
Author-email: dominik.mueller@informatik.uni-augsburg.de
License: GPLv3
Project-URL: Bug Tracker, https://github.com/frankkramer-lab/aucmedi/issues
Project-URL: Documentation, https://frankkramer-lab.github.io/aucmedi/reference/
Project-URL: Source Code, https://github.com/frankkramer-lab/aucmedi
Classifier: Programming Language :: Python :: 3
Classifier: Programming Language :: Python :: 3.10
Classifier: License :: OSI Approved :: GNU General Public License v3 (GPLv3)
Classifier: Operating System :: OS Independent
Classifier: Intended Audience :: Healthcare Industry
Classifier: Intended Audience :: Science/Research
Classifier: Topic :: Scientific/Engineering :: Artificial Intelligence
Classifier: Topic :: Scientific/Engineering :: Image Recognition
Classifier: Topic :: Scientific/Engineering :: Medical Science Apps.
Requires-Python: >=3.9
License-File: LICENSE.md
Requires-Dist: tensorflow >=2.14.0
Requires-Dist: numpy >=1.23.5
Requires-Dist: pillow >=10.2.0
Requires-Dist: albumentations >=1.3.0
Requires-Dist: pandas >=1.5.2
Requires-Dist: scikit-learn >=1.3.0
Requires-Dist: scikit-image >=0.21.0
Requires-Dist: lime >=0.2.0.1
Requires-Dist: pooch >=1.6.0
Requires-Dist: classification-models-3D >=1.0.10
Requires-Dist: Keras-Applications ==1.0.8
Requires-Dist: SimpleITK >=2.2.0
Requires-Dist: batchgenerators >=0.25
Requires-Dist: volumentations-aucmedi >=1.0.1
Requires-Dist: plotnine ==0.12.4
Requires-Dist: pathos >=0.3.0
